{
  "ProjectID": "PJV001",
  "OfficialID": "Mouse Kidney (FFPE)",
  "Platform": "Visium HD",
  "Instrument": "",
  "Species": "Mus musculus",
  "Tissue": "kidney",
  "Disease": "",
  "UploadDate": "2024/6/12",
  "EssayURL": "https://www.10xgenomics.com/datasets/visium-hd-cytassist-gene-expression-libraries-of-mouse-kidney",
  "EssayDOI": "",
  "Citation": "10x Genomics",
  "DataDownloadURL": "https://cf.10xgenomics.com/samples/spatial-exp/3.0.0/Visium_HD_Mouse_Kidney/Visium_HD_Mouse_Kidney_binned_outputs.tar.gz",
  "QualityLevel": 5,
  "ReadsPerSpot": 1282.8319448507434,
  "ReadsPer100um2": 501.10622845732166,
  "TotalReads": 100860096.0,
  "TotalSpots": 78623.0,
  "TotalGenes": 16813.0
}
